pyNotifications/__init__.py
pyNotifications/main.py
pyNotifications-1.0.0.dist-info/LICENSE.md
pyNotifications-1.0.0.dist-info/METADATA
pyNotifications-1.0.0.dist-info/WHEEL
pyNotifications-1.0.0.dist-info/top_level.txt
pyNotifications-1.0.0.dist-info/RECORD
