Metadata-Version: 2.1
Name: pyNotifications
Version: 1.0.0
Summary: Python package for sending telegram messages.
Author-email: Iratxe Moya <iratxe.moya@gmail.com>
Project-URL: Homepage, https://github.com/iratxeMoya/PythonNotifications
Project-URL: Bug Tracker, https://github.com/iratxeMoya/PythonNotifications/issues
Classifier: Development Status :: 3 - Alpha
Classifier: License :: OSI Approved :: MIT License
Classifier: Natural Language :: English
Classifier: Operating System :: OS Independent
Classifier: Programming Language :: Python
Classifier: Programming Language :: Python :: 3.9
Requires-Python: >=3.8
License-File: LICENSE.md
Requires-Dist: requests
